lenscorp/__init__.py
lenscorp/decorators.py
lenscorp/functions.py
lenscorp/biometrics/__init__.py
lenscorp/biometrics/evaluate.py
lenscorp/biometrics/logging.py
lenscorp/biometrics/metric.py
lenscorp/biometrics/plot.py
lenscorp/biometrics/utils.py
lenscorp-0.0.1.dist-info/LICENSE
lenscorp-0.0.1.dist-info/METADATA
lenscorp-0.0.1.dist-info/WHEEL
lenscorp-0.0.1.dist-info/top_level.txt
lenscorp-0.0.1.dist-info/RECORD
