Metadata-Version: 2.1
Name: lenscorp
Version: 0.0.1
Summary: AI Toolkit
Home-page: UNKNOWN
Author: LENS Corporation
Author-email: solutions@lenscorp.ai
License: MIT
Platform: UNKNOWN
License-File: LICENSE
Requires-Dist: requests
Requires-Dist: tqdm
Requires-Dist: numpy
Requires-Dist: matplotlib
Requires-Dist: seaborn
Requires-Dist: scipy
